adapi_sdk
test
