Metadata-Version: 2.1
Name: adapi-sdk
Version: 7.0.21
Summary: Sangfor AD API
Home-page: UNKNOWN
Author-email: 
License: UNKNOWN
Keywords: Swagger,Sangfor AD API
Platform: UNKNOWN
Requires-Dist: urllib3 (>=1.15)
Requires-Dist: six (>=1.10)
Requires-Dist: certifi
Requires-Dist: python-dateutil
